ashoks_data_tools-0.1.0.dist-info/licenses/LICENSE
data_tools/__init__.py
data_tools/cleaner.py
data_tools/transformer.py
data_tools/visualizer.py
data_tools/subpackage/__init__.py
data_tools/subpackage/advanced.py
ashoks_data_tools-0.1.0.dist-info/METADATA
ashoks_data_tools-0.1.0.dist-info/WHEEL
ashoks_data_tools-0.1.0.dist-info/top_level.txt
ashoks_data_tools-0.1.0.dist-info/RECORD
